cbapi/__init__.py
cbapi/attrdict.py
cbapi/auth.py
cbapi/connection.py
cbapi/errors.py
cbapi/event.py
cbapi/example_helpers.py
cbapi/live_response_api.py
cbapi/models.py
cbapi/oldmodels.py
cbapi/query.py
cbapi/six.py
cbapi/utils.py
cbapi/winerror.py
cbapi/cache/__init__.py
cbapi/cache/lru.py
cbapi/cache/redis.py
cbapi/protection/__init__.py
cbapi/protection/models.py
cbapi/protection/rest_api.py
cbapi/protection/models/connector.yaml
cbapi/protection/models/fileRule.yaml
cbapi/protection/models/notification.yaml
cbapi/protection/models/policy.yaml
cbapi/protection/models/trustedUser.yaml
cbapi/protection/models/user.yaml
cbapi/protection/models/userGroup.yaml
cbapi/response/__init__.py
cbapi/response/cblr.py
cbapi/response/event.py
cbapi/response/models.py
cbapi/response/query.py
cbapi/response/rest_api.py
cbapi/response/sensor_events.py
cbapi/response/threat_feed.py
cbapi/response/utils.py
cbapi/response/models/alert.yaml
cbapi/response/models/binary.yaml
cbapi/response/models/feed.yaml
cbapi/response/models/feedaction.yaml
cbapi/response/models/group-modify.yaml
cbapi/response/models/hash_blacklist.yaml
cbapi/response/models/ingress_filter.yaml
cbapi/response/models/investigation.yaml
cbapi/response/models/process.yaml
cbapi/response/models/sensor-builds.yaml
cbapi/response/models/sensorObject.yaml
cbapi/response/models/site.yaml
cbapi/response/models/tagged_event.yaml
cbapi/response/models/team.yaml
cbapi/response/models/throttle.yaml
cbapi/response/models/user.yaml
cbapi/response/models/watchlist-new.yaml
cbapi/response/models/watchlistaction.yaml
cbapi-2.0.0.data/scripts/cbapi
cbapi-2.0.0.data/scripts/cbapi-protection
cbapi-2.0.0.data/scripts/cbapi-response
cbapi-2.0.0.dist-info/LICENSE
cbapi-2.0.0.dist-info/METADATA
cbapi-2.0.0.dist-info/WHEEL
cbapi-2.0.0.dist-info/top_level.txt
cbapi-2.0.0.dist-info/RECORD
