Metadata-Version: 2.1
Name: cbapi
Version: 2.0.0
Summary: Carbon Black REST API Python Bindings
Home-page: https://github.com/carbonblack/cbapi-python
Author: Carbon Black
Author-email: dev-support@carbonblack.com
License: MIT
Platform: any
Classifier: Environment :: Web Environment
Classifier: Intended Audience :: Developers
Classifier: Operating System :: OS Independent
Classifier: Programming Language :: Python
Classifier: Topic :: Software Development :: Libraries :: Python Modules
License-File: LICENSE
Requires-Dist: requests
Requires-Dist: cachetools
Requires-Dist: pyyaml
Requires-Dist: pika
Requires-Dist: prompt-toolkit
Requires-Dist: pygments
Requires-Dist: python-dateutil
Requires-Dist: protobuf
Requires-Dist: solrq
Requires-Dist: validators
Requires-Dist: packaging
